thonnycontrib/202theme/__init__.py
thonny_202-0.1.dist-info/LICENSE
thonny_202-0.1.dist-info/METADATA
thonny_202-0.1.dist-info/WHEEL
thonny_202-0.1.dist-info/top_level.txt
thonny_202-0.1.dist-info/RECORD
